streamrandom/__init__.py
streamrandom/py.typed
streamrandom/test/__init__.py
streamrandom/test/test_streamrandom.py
streamrandom-2025.10.16.dist-info/licenses/LICENSE
streamrandom-2025.10.16.dist-info/WHEEL
streamrandom-2025.10.16.dist-info/METADATA
streamrandom-2025.10.16.dist-info/RECORD
