Metadata-Version: 2.4
Name: streamrandom
Version: 2025.10.16
Summary: Sometimes you want randomness that is I{unpredictable}, but still
Author-email: Glyph <glyph@twistedmatrix.com>
Requires-Python: >=3.10
Classifier: License :: OSI Approved :: MIT License
Classifier: Programming Language :: Python :: 3.10
Classifier: Programming Language :: Python :: 3.11
Classifier: Programming Language :: Python :: 3.12
Classifier: Programming Language :: Python :: 3.13
Classifier: Programming Language :: Python :: 3.14
License-File: LICENSE
Requires-Dist: cryptography
Requires-Dist: publication
Project-URL: Homepage, https://github.com/glyph/streamrandom
